ipyparallel/__init__.py
ipyparallel/_async.py
ipyparallel/_version.py
ipyparallel/datapub.py
ipyparallel/error.py
ipyparallel/joblib.py
ipyparallel/logger.py
ipyparallel/shellcmd.py
ipyparallel/traitlets.py
ipyparallel/util.py
ipyparallel/apps/__init__.py
ipyparallel/apps/baseapp.py
ipyparallel/apps/ipclusterapp.py
ipyparallel/apps/ipcontrollerapp.py
ipyparallel/apps/ipengineapp.py
ipyparallel/apps/iploggerapp.py
ipyparallel/apps/launcher.py
ipyparallel/apps/logwatcher.py
ipyparallel/client/__init__.py
ipyparallel/client/_joblib.py
ipyparallel/client/asyncresult.py
ipyparallel/client/client.py
ipyparallel/client/futures.py
ipyparallel/client/magics.py
ipyparallel/client/map.py
ipyparallel/client/remotefunction.py
ipyparallel/client/view.py
ipyparallel/cluster/__init__.py
ipyparallel/cluster/__main__.py
ipyparallel/cluster/_winhpcjob.py
ipyparallel/cluster/app.py
ipyparallel/cluster/cluster.py
ipyparallel/cluster/launcher.py
ipyparallel/cluster/shellcmd.py
ipyparallel/cluster/shellcmd_receive.py
ipyparallel/controller/__init__.py
ipyparallel/controller/__main__.py
ipyparallel/controller/app.py
ipyparallel/controller/broadcast_scheduler.py
ipyparallel/controller/dependency.py
ipyparallel/controller/dictdb.py
ipyparallel/controller/heartmonitor.py
ipyparallel/controller/hub.py
ipyparallel/controller/mongodb.py
ipyparallel/controller/scheduler.py
ipyparallel/controller/sqlitedb.py
ipyparallel/controller/task_scheduler.py
ipyparallel/engine/__init__.py
ipyparallel/engine/__main__.py
ipyparallel/engine/app.py
ipyparallel/engine/datapub.py
ipyparallel/engine/kernel.py
ipyparallel/engine/log.py
ipyparallel/engine/nanny.py
ipyparallel/labextension/package.json
ipyparallel/labextension/schemas/ipyparallel-labextension/package.json.orig
ipyparallel/labextension/schemas/ipyparallel-labextension/plugin.json
ipyparallel/labextension/static/296.87b6a53d1d5b3f17143e.js
ipyparallel/labextension/static/remoteEntry.8bfbc894f1978b53b2e2.js
ipyparallel/labextension/static/style.js
ipyparallel-9.0.0.dist-info/METADATA
ipyparallel-9.0.0.dist-info/WHEEL
ipyparallel-9.0.0.dist-info/entry_points.txt
ipyparallel-9.0.0.dist-info/licenses/COPYING.md
ipyparallel-9.0.0.dist-info/RECORD
