Metadata-Version: 2.3
Name: ipyparallel
Version: 9.0.0
Summary: Interactive Parallel Computing with IPython
Project-URL: Homepage, https://ipython.org
Author-email: IPython Development Team <ipython-dev@scipy.org>
License: # Licensing terms
License-File: COPYING.md
Keywords: Interactive,Interpreter,Parallel,Shell
Classifier: Framework :: Jupyter
Classifier: Framework :: Jupyter :: JupyterLab
Classifier: Framework :: Jupyter :: JupyterLab :: 4
Classifier: Framework :: Jupyter :: JupyterLab :: Extensions
Classifier: Framework :: Jupyter :: JupyterLab :: Extensions :: Prebuilt
Classifier: Intended Audience :: Developers
Classifier: Intended Audience :: Science/Research
Classifier: Intended Audience :: System Administrators
Classifier: License :: OSI Approved :: BSD License
Classifier: Programming Language :: Python
Classifier: Programming Language :: Python :: 3.8
Requires-Python: >=3.8
Requires-Dist: decorator
Requires-Dist: importlib-metadata>=3.6; python_version < '3.10'
Requires-Dist: ipykernel>=6.9.1
Requires-Dist: ipython>=5
Requires-Dist: jupyter-client>=7
Requires-Dist: psutil
Requires-Dist: python-dateutil>=2.1
Requires-Dist: pyzmq>=25
Requires-Dist: tornado>=6.1
Requires-Dist: tqdm
Requires-Dist: traitlets>=5
Provides-Extra: benchmark
Requires-Dist: asv; extra == 'benchmark'
Provides-Extra: labextension
Requires-Dist: jupyter-server; extra == 'labextension'
Requires-Dist: jupyterlab>=3; extra == 'labextension'
Provides-Extra: nbext
Requires-Dist: jupyter-server; extra == 'nbext'
Requires-Dist: notebook; extra == 'nbext'
Provides-Extra: retroextension
Requires-Dist: jupyter-server; extra == 'retroextension'
Requires-Dist: retrolab; extra == 'retroextension'
Provides-Extra: serverextension
Requires-Dist: jupyter-server; extra == 'serverextension'
Provides-Extra: test
Requires-Dist: ipython[test]; extra == 'test'
Requires-Dist: pytest; extra == 'test'
Requires-Dist: pytest-asyncio; extra == 'test'
Requires-Dist: pytest-cov; extra == 'test'
Requires-Dist: testpath; extra == 'test'
